cobra_db/__init__.py
cobra_db/dataset_mod.py
cobra_db/deid.py
cobra_db/deid_recipe.txt
cobra_db/deid_recipe_mr.txt
cobra_db/encrypt.py
cobra_db/enums.py
cobra_db/filesystem.py
cobra_db/model.py
cobra_db/mongo_dao.py
cobra_db/scripts/__init__.py
cobra_db/scripts/pseudonymize_image_metadata.py
cobra_db/scripts/stage_1_ingest_images.py
cobra_db/scripts/stage_2.py
cobra_db/scripts/stage_2_group_patients.py
cobra_db/scripts/stage_2_group_series.py
cobra_db/scripts/stage_2_group_studies.py
cobra_db/scripts/utils.py
cobra_db/types.py
cobra_db/utils.py
cobra_db-0.4.6.dist-info/LICENSE
cobra_db-0.4.6.dist-info/METADATA
cobra_db-0.4.6.dist-info/WHEEL
cobra_db-0.4.6.dist-info/entry_points.txt
cobra_db-0.4.6.dist-info/RECORD
