Metadata-Version: 2.1
Name: cobra_db
Version: 0.4.6
Summary: COnsolidated BReast cancer Analysis DataBase
License: Apache-2.0
Author: Fernando Cossio
Requires-Python: >=3.8,<4.0
Classifier: License :: OSI Approved :: Apache Software License
Classifier: Programming Language :: Python :: 3
Classifier: Programming Language :: Python :: 3.8
Classifier: Programming Language :: Python :: 3.9
Classifier: Programming Language :: Python :: 3.10
Classifier: Programming Language :: Python :: 3.11
Classifier: Programming Language :: Python :: 3.12
Requires-Dist: deid (>=0.2.36,<0.3.0)
Requires-Dist: dnspython (>=2.2.1,<3.0.0)
Requires-Dist: numpy (>=1.23.2,<2.0.0)
Requires-Dist: pyaml-env (>=1.1.5,<2.0.0)
Requires-Dist: pycryptodome (>=3.15.0,<4.0.0)
Requires-Dist: pydicom (>=2.3.0,<3.0.0)
Requires-Dist: pymongo[srv] (>=4.2.0,<5.0.0)
Requires-Dist: tqdm (>=4.64.1,<5.0.0)
